musket_core/__init__.py
musket_core/analize.py
musket_core/builtin_datasets.py
musket_core/builtin_trainables.py
musket_core/caches.py
musket_core/callback_module.py
musket_core/cli.py
musket_core/clr_callback.py
musket_core/coders.py
musket_core/configloader.py
musket_core/context.py
musket_core/crf.py
musket_core/dataset_analis.py
musket_core/dataset_analizers.py
musket_core/dataset_visualizers.py
musket_core/datasets.py
musket_core/datasources.py
musket_core/deps_download.py
musket_core/dsconfig.py
musket_core/experiment.py
musket_core/export.py
musket_core/extras.py
musket_core/fit.py
musket_core/generic.py
musket_core/generic_config.py
musket_core/genericcsv.py
musket_core/gradientboosting.py
musket_core/hyper.py
musket_core/image_datasets.py
musket_core/inference.py
musket_core/inspectProject.py
musket_core/introspector.py
musket_core/java_server.py
musket_core/launch.py
musket_core/logger.py
musket_core/losses.py
musket_core/lr_finder.py
musket_core/lr_variation_callback.py
musket_core/metrics.py
musket_core/model.py
musket_core/multigpu_checkpoint.py
musket_core/musket_client.py
musket_core/net_declaration.py
musket_core/parralel.py
musket_core/predictions.py
musket_core/preprocessing.py
musket_core/projects.py
musket_core/quasymodels.py
musket_core/splits.py
musket_core/structure_constants.py
musket_core/task.py
musket_core/tasks.py
musket_core/templating.py
musket_core/test.py
musket_core/tool_set.py
musket_core/tools.py
musket_core/utils.py
musket_core/visualization.py
musket_core/examples/bidirectional.yaml
musket_core/examples/conditional.yaml
musket_core/examples/example1.yaml
musket_core/examples/example2.1.yaml
musket_core/examples/example2.2.yaml
musket_core/examples/example2.3.yaml
musket_core/examples/example2.4.yaml
musket_core/examples/example2.5.yaml
musket_core/examples/example2.6.yaml
musket_core/examples/example2.7.yaml
musket_core/examples/example2.8.yaml
musket_core/examples/example2.9.yaml
musket_core/examples/example2.yaml
musket_core-0.498.dist-info/LICENSE
musket_core-0.498.dist-info/METADATA
musket_core-0.498.dist-info/WHEEL
musket_core-0.498.dist-info/dependency_links.txt
musket_core-0.498.dist-info/entry_points.txt
musket_core-0.498.dist-info/top_level.txt
musket_core-0.498.dist-info/RECORD
