Metadata-Version: 2.1
Name: musket-core
Version: 0.498
Summary: The core of Musket ML
Home-page: https://github.com/musket-ml/musket_core
Author: Petrochenko Pavel
Author-email: petrochenko.pavel.a@gmail.com
License: MIT
Platform: UNKNOWN
Requires-Dist: hyperopt (<=0.2.1,>=0.1.2)
Requires-Dist: PyYAML (<=5.1.2,>=3.13)
Requires-Dist: numpy (<=1.17.3,>=1.15.4)
Requires-Dist: Keras (<=2.3.1,>=2.2.4)
Requires-Dist: tqdm (<=4.36.1,>=4.28.1)
Requires-Dist: pandas (<=0.25.2,>=0.23.4)
Requires-Dist: scikit-learn (<=0.21.3,>=0.20.2)
Requires-Dist: scikit-image (==0.15.0)
Requires-Dist: Pillow (<=6.2.1,>=5.4.0)
Requires-Dist: scikit-image (>=0.14.2)
Requires-Dist: Shapely (<=1.6.4.post2,>=1.6.4.post1)
Requires-Dist: imgaug (==0.3.0)
Requires-Dist: lightgbm (<=2.3.0,>=2.2.3)
Requires-Dist: py4j (==0.10.8.1)
Requires-Dist: async-promises (==1.1.1)
Requires-Dist: scipy (<=1.3.1,>=1.2.0)
Requires-Dist: matplotlib (<=3.1.1,>=3.0.2)
Requires-Dist: imageio (<=2.6.1,>=2.4.1)
Requires-Dist: h5py (<=2.10.0,>=2.9.0)
Requires-Dist: opencv-python (<=4.1.1.26,>=3.4.5.20)
Requires-Dist: Cython (<=0.29.13,>=0.29.2)
Requires-Dist: segmentation-models (<=0.2.1,<=0.2.1image-classifiers>=0.2.0,>=0.2.0)
